simples.py
python_simples-1.0.0.dist-info/METADATA
python_simples-1.0.0.dist-info/WHEEL
python_simples-1.0.0.dist-info/entry_points.txt
python_simples-1.0.0.dist-info/top_level.txt
python_simples-1.0.0.dist-info/RECORD
