Metadata-Version: 2.1
Name: python-simples
Version: 1.0.0
Summary: A Python Library that Helps You Do Some Simple Works.
Home-page: https://github.com/dafangs/python-simples
Author: dafangs
Author-email: dafangs@hotmail.com
License: MIT
Platform: UNKNOWN
Classifier: License :: OSI Approved :: MIT License
Classifier: Programming Language :: Python
Classifier: Programming Language :: Python :: 3
Classifier: Programming Language :: Python :: 3.6
Classifier: Programming Language :: Python :: Implementation :: CPython
Classifier: Programming Language :: Python :: Implementation :: PyPy
Requires-Python: >=3.6.0
Requires-Dist: sh
